{
  "id": "template_project_manager_ic",
  "template_name": "Project Manager (I&C)",
  "role_level": 5,
  "role_level_title": "Project Manager",
  "trade": "Instrumentation",
  "role_description": "Project Manager overseeing the instrumentation and controls scope of an industrial construction project. Manages schedule, budget, vendor coordination, client relations, and ensures overall I&C project delivery. Coordinates with the instrument supervisor to ensure milestones are met, loop checks are on schedule, and commissioning activities are properly sequenced.",
  "report_focus": "When structuring this person's reports, look for: project milestones, budget status, schedule updates, client communications, vendor performance, RFI status, change orders, instrument procurement, loop check progress, commissioning readiness, and risk items.",
  "output_sections": [
    "Project Status Summary",
    "Schedule & Milestones",
    "Budget & Cost Tracking",
    "Client Communications",
    "Vendor & Procurement Status",
    "RFIs & Change Orders",
    "Loop Check Progress",
    "Commissioning Readiness",
    "Risk Items & Mitigation",
    "Action Items"
  ],
  "vocabulary": {
    "terms": ["P&ID", "loop diagram", "loop check", "loop sheet", "instrument index", "instrument list", "hook-up drawing", "junction box", "marshalling cabinet", "DCS", "PLC", "SCADA", "SIS", "safety instrumented system", "transmitter", "pressure transmitter", "temperature transmitter", "level transmitter", "flow transmitter", "control valve", "actuator", "positioner", "I/P converter", "RTD", "thermocouple", "thermowell", "orifice plate", "flow element", "radar level", "guided wave radar", "ultrasonic", "magnetic flow meter", "Coriolis", "vortex meter", "turbine meter", "pressure gauge", "temperature gauge", "level gauge", "sight glass", "PSV", "pressure safety valve", "rupture disc", "solenoid valve", "shutdown valve", "ESD", "emergency shutdown", "interlock", "permissive", "alarm", "setpoint", "range", "span", "calibration", "HART", "fieldbus", "Foundation Fieldbus", "Profibus", "4-20mA", "signal", "analog input", "analog output", "digital input", "digital output", "IO count", "IO list", "cable schedule", "instrument cable", "multi-pair cable", "thermocouple cable", "tubing", "instrument tubing", "SS tubing", "tube fitting", "Swagelok", "impulse line", "manifold", "5-valve manifold", "3-valve manifold", "process connection", "tap", "root valve", "isolation valve", "blowdown valve", "air supply", "instrument air", "pneumatic", "hazardous area", "Class I Div 1", "Class I Div 2", "explosion proof", "intrinsically safe", "IS barrier", "zener barrier", "galvanic isolator", "area classification", "ATEX", "IECEx", "contract", "change order", "CO", "extra work", "T&M", "time and materials", "lump sum", "unit rate", "backcharge", "scope", "scope of work", "SOW", "scope change", "budget", "estimate", "forecast", "variance", "contingency", "earned value", "EV", "CPI", "cost performance index", "SPI", "schedule performance index", "milestone", "baseline", "critical path", "float", "look-ahead", "S-curve", "percent complete", "progress", "EPC", "engineering procurement construction", "FEED", "front end engineering design", "owner", "client", "contractor", "subcontractor", "GC", "general contractor", "RFI", "request for information", "RFP", "request for proposal", "submittal", "transmittal", "MOC", "management of change", "FCN", "field change notice", "NCR", "non-conformance report", "QA", "quality assurance", "QC", "quality control", "ITP", "inspection and test plan", "FAT", "factory acceptance test", "SAT", "site acceptance test", "turnover", "turnover package", "mechanical completion", "MC", "pre-commissioning", "commissioning", "RFCC", "RFSU", "ready for start-up", "handover", "substantial completion", "final completion", "warranty", "retention", "liquidated damages", "LD", "mobilization", "demobilization", "procurement", "lead time", "expediting", "vendor", "vendor management", "vendor data", "punch list", "A punch", "B punch", "C punch", "risk register", "risk mitigation", "lessons learned", "KPI", "key performance indicator", "dashboard", "progress report", "daily report", "weekly report", "monthly report", "HSE", "health safety environment"]
  },
  "safety_rules": [
    "Establish and communicate the project safety program — zero incidents is the only acceptable target",
    "Ensure adequate HSE staffing and resources are budgeted for the instrumentation scope",
    "Review project safety metrics weekly — TRIR, DART, near-miss ratio, and safety observations",
    "Include safety performance as a key criterion in subcontractor qualification and evaluation",
    "Support stop work authority at all levels — no schedule or cost pressure justifies unsafe work",
    "Ensure all instrument personnel meet minimum safety training requirements before mobilization",
    "Review and approve the site-specific safety plan before instrument construction begins",
    "Attend and support site safety stand-downs and safety awareness campaigns",
    "Monitor incident investigations and ensure corrective actions are implemented and closed out",
    "Ensure commissioning safety procedures are reviewed and approved before system energization",
    "Coordinate with the client on safety requirements, permit-to-work systems, and site access",
    "Do not compress safety activities for schedule recovery — safety is non-negotiable",
    "Ensure proper area classification documentation is complete before work in hazardous areas",
    "Review lift plans and SIMOPS plans that impact the I&C scope",
    "Maintain project safety records and documentation for client and regulatory compliance",
    "Brief all project team members on emergency procedures and evacuation protocols",
    "Ensure drug and alcohol testing programs are enforced per project and client requirements",
    "Lead by example — wear proper PPE during all field visits and demonstrate safety commitment",
    "Include safety performance in project close-out reports and lessons learned",
    "Verify that vendor and third-party personnel comply with project safety requirements"
  ],
  "safety_vocabulary": [
    "PPE",
    "HSE",
    "health safety environment",
    "EHS",
    "safety program",
    "safety plan",
    "LOTO",
    "lockout tagout",
    "JSA",
    "job safety analysis",
    "incident",
    "near-miss",
    "recordable",
    "lost time",
    "fatality",
    "TRIR",
    "total recordable incident rate",
    "DART",
    "days away restricted transferred",
    "EMR",
    "experience modification rate",
    "OSHA",
    "OSHA 30",
    "root cause analysis",
    "corrective action",
    "preventive action",
    "CAPA",
    "stop work authority",
    "SWA",
    "safety stand-down",
    "safety audit",
    "safety culture",
    "behavior-based safety",
    "BBS",
    "safety observation",
    "muster point",
    "evacuation",
    "emergency action plan",
    "EAP",
    "confined space",
    "hot work",
    "fall protection",
    "arc flash",
    "area classification",
    "hazardous area",
    "SIS",
    "safety instrumented system",
    "SIL",
    "MOC",
    "management of change",
    "SIMOPS",
    "lift plan",
    "fit for duty",
    "drug test",
    "subcontractor safety qualification",
    "ISNetworld",
    "Avetta",
    "TWIC",
    "NEC",
    "NFPA 70E"
  ],
  "tools_and_equipment": [
    "Laptop computer — for project management, scheduling, cost control, and client correspondence",
    "Scheduling software — Primavera P6 or Microsoft Project for baseline and progress schedules",
    "Cost management system — for budget tracking, earned value analysis, forecasting, and variance reporting",
    "Document control system — for managing RFIs, change orders, submittals, transmittals, and vendor data",
    "Contract management tools — for tracking contract terms, change orders, billing, and retention",
    "Procurement tracking system — for monitoring instrument procurement, deliveries, and lead times",
    "Reporting dashboards — for project KPIs, safety metrics, progress curves, and earned value",
    "Microsoft Office suite — Word, Excel, PowerPoint for reports, cost analysis, and presentations",
    "Email and calendar — Outlook or equivalent for client communication and meeting management",
    "Video conferencing — Teams, Zoom, or WebEx for remote client, vendor, and engineering meetings",
    "Risk register — for identifying, tracking, and mitigating project risks",
    "Action item tracker — for managing and closing out project and meeting action items",
    "Turnover and commissioning tracking system — for monitoring system completions and handover status",
    "Safety management system — for incident reporting, safety metrics, and compliance tracking",
    "Tablet or iPad — for field walks, progress verification, and digital punch list reviews",
    "Digital camera — for documenting project progress and site conditions",
    "Drawing management system — for tracking P&ID revisions, instrument index, and as-built status",
    "Vehicle — for site travel, client office visits, and vendor facility inspections",
    "PPE — hard hat, safety glasses, steel-toe boots, FR clothing for all field visits",
    "Presentation equipment — for project review meetings, client presentations, and lessons learned sessions"
  ]
}
